{
"Performance Class":"5",
"Drivetrain":"FWD",
"100-200 km/h":13.1,
"Value":32000,
"0-200 km/h":19.1,
"TorquePeakRPM":"1900 - 3000",
"Transmission":"Automatic",
"Description":"The Diesel Cup was a competition created by Hirochi as a showcase for the Diesel Sunburst, it hosted 25 cars on short races. The funny thing was that there were no professional drivers, everyone could race by renting the car for a racing season",
"Configuration":"#10 'Hirochi Racing' Diesel Cup Car (DCT)",
"0-100 mph":12,
"Weight":1335,
"60-100 mph":6.3,
"0-60 mph":5.7,
"Config Type":"Custom",
"100-0 km/h":38,
"PowerPeakRPM":"3400 - 4400",
"default_color":"Pearl White",
"Torque":582.156,
"Off-Road Score":28,
"Power":253.708,
"Weight/Power":5.27668,
"60-0 mph":108.4,
"0-100 km/h":6,
"Top Speed":64.8745
}